awslabs/__init__.py
awslabs/amazon_keyspaces_mcp_server/__init__.py
awslabs/amazon_keyspaces_mcp_server/client.py
awslabs/amazon_keyspaces_mcp_server/config.py
awslabs/amazon_keyspaces_mcp_server/consts.py
awslabs/amazon_keyspaces_mcp_server/llm_context.py
awslabs/amazon_keyspaces_mcp_server/models.py
awslabs/amazon_keyspaces_mcp_server/server.py
awslabs/amazon_keyspaces_mcp_server/services.py
awslabs_amazon_keyspaces_mcp_server-0.0.12.dist-info/METADATA
awslabs_amazon_keyspaces_mcp_server-0.0.12.dist-info/WHEEL
awslabs_amazon_keyspaces_mcp_server-0.0.12.dist-info/entry_points.txt
awslabs_amazon_keyspaces_mcp_server-0.0.12.dist-info/licenses/LICENSE
awslabs_amazon_keyspaces_mcp_server-0.0.12.dist-info/licenses/NOTICE
awslabs_amazon_keyspaces_mcp_server-0.0.12.dist-info/RECORD
