Metadata-Version: 2.4
Name: awslabs.amazon-keyspaces-mcp-server
Version: 0.0.12
Summary: An Amazon Keyspaces (for Apache Cassandra) MCP server for interacting with Amazon Keyspaces and Apache Cassandra.
Project-URL: homepage, https://awslabs.github.io/mcp/
Project-URL: docs, https://awslabs.github.io/mcp/servers/amazon-keyspaces-mcp-server/
Project-URL: documentation, https://awslabs.github.io/mcp/servers/amazon-keyspaces-mcp-server/
Project-URL: repository, https://github.com/awslabs/mcp.git
Project-URL: changelog, https://github.com/awslabs/mcp/blob/main/src/amazon-keyspaces-mcp-server/CHANGELOG.md
Author: Amazon Web Services
Author-email: AWSLabs MCP <203918161+awslabs-mcp@users.noreply.github.com>, Joel Shepherd <shepherd@amazon.com>
License: Apache-2.0
License-File: LICENSE
License-File: NOTICE
Classifier: License :: OSI Approved :: Apache Software License
Classifier: Operating System :: OS Independent
Classifier: Programming Language :: Python
Classifier: Programming Language :: Python :: 3
Classifier: Programming Language :: Python :: 3.10
Classifier: Programming Language :: Python :: 3.11
Requires-Python: <3.12,>=3.10
Requires-Dist: boto3>=1.37.27
Requires-Dist: cassandra-driver>=3.25.0
Requires-Dist: fastmcp>=2.14.0
Requires-Dist: loguru>=0.7.0
Requires-Dist: mcp>=1.23.0
Requires-Dist: pydantic>=2.10.6
Requires-Dist: python-dotenv>=1.0.0
